<annotation>
	<folder>cups</folder>
	<filename>BmF7oqNgPIo.jpg</filename>
	<path>C:\myProj\ImageAnalysisAds\ImageAnalysisAds.Crawler\training_img\cups\BmF7oqNgPIo.jpg</path>
	<source>
		<database>Unknown</database>
	</source>
	<size>
		<width>150</width>
		<height>150</height>
		<depth>3</depth>
	</size>
	<segmented>0</segmented>
	<object>
		<name>cups</name>
		<pose>Unspecified</pose>
		<truncated>0</truncated>
		<difficult>0</difficult>
		<bndbox>
			<xmin>75</xmin>
			<ymin>48</ymin>
			<xmax>145</xmax>
			<ymax>145</ymax>
		</bndbox>
	</object>
	<object>
		<name>cups</name>
		<pose>Unspecified</pose>
		<truncated>0</truncated>
		<difficult>0</difficult>
		<bndbox>
			<xmin>23</xmin>
			<ymin>36</ymin>
			<xmax>93</xmax>
			<ymax>107</ymax>
		</bndbox>
	</object>
</annotation>
