<annotation>
	<folder>cups</folder>
	<filename>BmGNHPIF4Te.jpg</filename>
	<path>C:\myProj\ImageAnalysisAds\ImageAnalysisAds.Crawler\training_img\cups\BmGNHPIF4Te.jpg</path>
	<source>
		<database>Unknown</database>
	</source>
	<size>
		<width>150</width>
		<height>150</height>
		<depth>3</depth>
	</size>
	<segmented>0</segmented>
	<object>
		<name>cups</name>
		<pose>Unspecified</pose>
		<truncated>0</truncated>
		<difficult>0</difficult>
		<bndbox>
			<xmin>79</xmin>
			<ymin>3</ymin>
			<xmax>140</xmax>
			<ymax>45</ymax>
		</bndbox>
	</object>
	<object>
		<name>cups</name>
		<pose>Unspecified</pose>
		<truncated>1</truncated>
		<difficult>0</difficult>
		<bndbox>
			<xmin>85</xmin>
			<ymin>114</ymin>
			<xmax>150</xmax>
			<ymax>149</ymax>
		</bndbox>
	</object>
	<object>
		<name>cups</name>
		<pose>Unspecified</pose>
		<truncated>0</truncated>
		<difficult>0</difficult>
		<bndbox>
			<xmin>20</xmin>
			<ymin>2</ymin>
			<xmax>75</xmax>
			<ymax>44</ymax>
		</bndbox>
	</object>
	<object>
		<name>cups</name>
		<pose>Unspecified</pose>
		<truncated>1</truncated>
		<difficult>0</difficult>
		<bndbox>
			<xmin>9</xmin>
			<ymin>115</ymin>
			<xmax>80</xmax>
			<ymax>150</ymax>
		</bndbox>
	</object>
	<object>
		<name>cups</name>
		<pose>Unspecified</pose>
		<truncated>0</truncated>
		<difficult>0</difficult>
		<bndbox>
			<xmin>2</xmin>
			<ymin>89</ymin>
			<xmax>73</xmax>
			<ymax>123</ymax>
		</bndbox>
	</object>
	<object>
		<name>cups</name>
		<pose>Unspecified</pose>
		<truncated>0</truncated>
		<difficult>0</difficult>
		<bndbox>
			<xmin>7</xmin>
			<ymin>59</ymin>
			<xmax>71</xmax>
			<ymax>93</ymax>
		</bndbox>
	</object>
	<object>
		<name>cups</name>
		<pose>Unspecified</pose>
		<truncated>0</truncated>
		<difficult>0</difficult>
		<bndbox>
			<xmin>78</xmin>
			<ymin>89</ymin>
			<xmax>149</xmax>
			<ymax>125</ymax>
		</bndbox>
	</object>
</annotation>
