<annotation>
	<folder>cups</folder>
	<filename>BmI--NllkHT.jpg</filename>
	<path>C:\myProj\ImageAnalysisAds\ImageAnalysisAds.Crawler\training_img\cups\BmI--NllkHT.jpg</path>
	<source>
		<database>Unknown</database>
	</source>
	<size>
		<width>150</width>
		<height>150</height>
		<depth>3</depth>
	</size>
	<segmented>0</segmented>
	<object>
		<name>cups</name>
		<pose>Unspecified</pose>
		<truncated>0</truncated>
		<difficult>0</difficult>
		<bndbox>
			<xmin>6</xmin>
			<ymin>11</ymin>
			<xmax>70</xmax>
			<ymax>69</ymax>
		</bndbox>
	</object>
	<object>
		<name>cups</name>
		<pose>Unspecified</pose>
		<truncated>1</truncated>
		<difficult>0</difficult>
		<bndbox>
			<xmin>65</xmin>
			<ymin>112</ymin>
			<xmax>89</xmax>
			<ymax>150</ymax>
		</bndbox>
	</object>
</annotation>
